benutils/misc/__init__.py
benutils/misc/data_file_handler.py
benutils/misc/datacontainer.py
benutils/misc/mjdutils.py
benutils/misc/usb_utils.py
benutils/sdr/__init__.py
benutils/sdr/decimator.py
benutils/sdr/limiter.py
benutils/sdr/median.py
benutils/sdr/mux.py
benutils/sdr/outlier_detector.py
benutils/sdr/pid.py
benutils/sdr/qdecimator.py
benutils/sdr/qmedian.py
benutils/sdr/qmux.py
benutils/sdr/qoutlier_detector.py
benutils/sdr/qpid.py
benutils/sdr/summator.py
benutils/widget/__init__.py
benutils/widget/flowlayout.py
benutils/widget/myqcombobox.py
benutils/widget/myqlabel.py
benutils/widget/qled.py
benutils/widget/real_time_plot.py
benutils-0.5.5.dist-info/LICENSE.txt
benutils-0.5.5.dist-info/METADATA
benutils-0.5.5.dist-info/WHEEL
benutils-0.5.5.dist-info/top_level.txt
benutils-0.5.5.dist-info/RECORD
